agent_flows_mcp/__init__.py
agent_flows_mcp/cli.py
agent_flows_mcp/config.py
agent_flows_mcp/flow_manager.py
agent_flows_mcp/models.py
agent_flows_mcp/server.py
agent_flows_mcp/system_variables.py
agent_flows_mcp/tool_generator.py
realtimex_agent_flows_mcp_server-0.1.0.dist-info/METADATA
realtimex_agent_flows_mcp_server-0.1.0.dist-info/WHEEL
realtimex_agent_flows_mcp_server-0.1.0.dist-info/entry_points.txt
realtimex_agent_flows_mcp_server-0.1.0.dist-info/RECORD
