Metadata-Version: 2.4
Name: realtimex-agent-flows-mcp-server
Version: 0.1.0
Summary: MCP server for RealTimeX Agent Flows - dynamically provides tools based on available flows
Project-URL: Homepage, https://github.com/realtimex/agent-flows-mcp-server
Project-URL: Documentation, https://github.com/realtimex/agent-flows-mcp-server#readme
Project-URL: Repository, https://github.com/realtimex/agent-flows-mcp-server
Project-URL: Issues, https://github.com/realtimex/agent-flows-mcp-server/issues
Author-email: RealTimeX <support@realtimex.com>
License: MIT
Keywords: agent-flows,automation,mcp,realtimex,workflow
Classifier: Development Status :: 4 - Beta
Classifier: Intended Audience :: Developers
Classifier: License :: OSI Approved :: MIT License
Classifier: Programming Language :: Python :: 3
Classifier: Programming Language :: Python :: 3.11
Classifier: Programming Language :: Python :: 3.12
Classifier: Topic :: Software Development :: Libraries :: Python Modules
Classifier: Topic :: System :: Networking
Requires-Python: >=3.11
Requires-Dist: anyio>=4.0.0
Requires-Dist: click>=8.0.0
Requires-Dist: httpx>=0.25.0
Requires-Dist: mcp[cli]>=1.2.0
Requires-Dist: pydantic>=2.0.0
Requires-Dist: realtimex-agent-flows
Requires-Dist: structlog>=23.0.0
Provides-Extra: dev
Requires-Dist: black>=23.0.0; extra == 'dev'
Requires-Dist: mypy>=1.5.0; extra == 'dev'
Requires-Dist: pre-commit>=3.0.0; extra == 'dev'
Requires-Dist: pytest-asyncio>=0.21.0; extra == 'dev'
Requires-Dist: pytest-mock>=3.12.0; extra == 'dev'
Requires-Dist: pytest>=7.0.0; extra == 'dev'
Requires-Dist: ruff>=0.1.0; extra == 'dev'
